rag_retriever/__init__.py
rag_retriever/cli.py
rag_retriever/main.py
rag_retriever/config/config.yaml
rag_retriever/crawling/__init__.py
rag_retriever/crawling/content_cleaner.py
rag_retriever/crawling/crawl4ai_crawler.py
rag_retriever/crawling/exceptions.py
rag_retriever/crawling/playwright_crawler.py
rag_retriever/document_processor/__init__.py
rag_retriever/document_processor/confluence_loader.py
rag_retriever/document_processor/github_loader.py
rag_retriever/document_processor/image_loader.py
rag_retriever/document_processor/local_loader.py
rag_retriever/document_processor/vision_analyzer.py
rag_retriever/mcp/__init__.py
rag_retriever/mcp/server.py
rag_retriever/search/__init__.py
rag_retriever/search/searcher.py
rag_retriever/search/web_search.py
rag_retriever/static/CTF-logo.jpg
rag_retriever/ui/__init__.py
rag_retriever/ui/app.py
rag_retriever/utils/__init__.py
rag_retriever/utils/config.py
rag_retriever/utils/system_validation.py
rag_retriever/utils/windows.py
rag_retriever/vectorstore/__init__.py
rag_retriever/vectorstore/store.py
rag_retriever-0.4.1.dist-info/licenses/LICENSE
scripts/install.py
scripts/organize_pdfs.py
scripts/run_ui.py
scripts/test_github_loader.py
scripts/test_pdf_processing.py
rag_retriever-0.4.1.dist-info/METADATA
rag_retriever-0.4.1.dist-info/WHEEL
rag_retriever-0.4.1.dist-info/entry_points.txt
rag_retriever-0.4.1.dist-info/top_level.txt
rag_retriever-0.4.1.dist-info/RECORD
