Metadata-Version: 2.4
Name: rag-retriever
Version: 0.4.1
Summary: A tool for crawling, indexing, and semantically searching web content with RAG capabilities
Author-email: Tim Kitchens <codingthefuturewithai@gmail.com>
License: MIT
Keywords: ai,rag,embeddings,semantic-search,web-crawler,vector-store
Classifier: Development Status :: 3 - Alpha
Classifier: Intended Audience :: Developers
Classifier: License :: OSI Approved :: MIT License
Classifier: Programming Language :: Python :: 3
Classifier: Programming Language :: Python :: 3.10
Classifier: Programming Language :: Python :: 3.11
Classifier: Programming Language :: Python :: 3.12
Classifier: Topic :: Software Development :: Libraries :: Python Modules
Requires-Python: <3.13,>=3.10
License-File: LICENSE
Requires-Dist: beautifulsoup4==4.12.3
Requires-Dist: chromadb==0.5.23
Requires-Dist: duckduckgo-search>=4.1.1
Requires-Dist: langchain==0.3.18
Requires-Dist: langchain-community==0.3.17
Requires-Dist: langchain-core==0.3.34
Requires-Dist: langchain-chroma==0.1.4
Requires-Dist: langchain-openai==0.2.14
Requires-Dist: langchain-google-community>=0.0.11
Requires-Dist: lxml==5.3.0
Requires-Dist: openai==1.59.4
Requires-Dist: playwright>=1.49.0
Requires-Dist: pypdf==4.1.0
Requires-Dist: pyyaml==6.0.2
Requires-Dist: importlib-resources>=6.1.1
Requires-Dist: unstructured[pdf]>=0.12.0
Requires-Dist: pillow>=10.2.0
Requires-Dist: pymupdf>=1.23.8
Requires-Dist: pytesseract>=0.3.10
Requires-Dist: atlassian-python-api>=3.41.4
Requires-Dist: markdownify>=0.11.6
Requires-Dist: gitpython>=3.1.42
Requires-Dist: mcp>=1.0.0
Requires-Dist: mcp[cli]>=1.0.0
Requires-Dist: anyio>=4.5
Requires-Dist: starlette>=0.36.0
Requires-Dist: uvicorn>=0.27.0
Requires-Dist: streamlit>=1.32.0
Requires-Dist: pandas>=2.2.0
Requires-Dist: plotly>=5.19.0
Requires-Dist: crawl4ai>=0.4.0
Provides-Extra: dev
Requires-Dist: pytest==7.3.0; extra == "dev"
Requires-Dist: pytest-cov>=4.1.0; extra == "dev"
Dynamic: license-file
